odoo/addons/website_form_builder/README.rst
odoo/addons/website_form_builder/__init__.py
odoo/addons/website_form_builder/__manifest__.py
odoo/addons/website_form_builder/demo/assets.xml
odoo/addons/website_form_builder/demo/ir_model.xml
odoo/addons/website_form_builder/i18n/es.po
odoo/addons/website_form_builder/i18n/website_form_builder.pot
odoo/addons/website_form_builder/migrations/11.0.1.2.0/post-migrate.py
odoo/addons/website_form_builder/readme/CONFIGURE.rst
odoo/addons/website_form_builder/readme/CONTRIBUTORS.rst
odoo/addons/website_form_builder/readme/CREDITS.rst
odoo/addons/website_form_builder/readme/DESCRIPTION.rst
odoo/addons/website_form_builder/readme/INSTALL.rst
odoo/addons/website_form_builder/readme/ROADMAP.rst
odoo/addons/website_form_builder/readme/USAGE.rst
odoo/addons/website_form_builder/static/description/icon.png
odoo/addons/website_form_builder/static/description/icon.svg
odoo/addons/website_form_builder/static/description/index.html
odoo/addons/website_form_builder/static/src/css/website_form_builder.less
odoo/addons/website_form_builder/static/src/js/snippets.js
odoo/addons/website_form_builder/static/src/js/tour.js
odoo/addons/website_form_builder/static/src/js/widgets.js
odoo/addons/website_form_builder/static/src/xml/snippets.xml
odoo/addons/website_form_builder/static/src/xml/widgets.xml
odoo/addons/website_form_builder/templates/assets.xml
odoo/addons/website_form_builder/templates/snippets.xml
odoo/addons/website_form_builder/tests/__init__.py
odoo/addons/website_form_builder/tests/test_ui.py
odoo/addons/website_form_builder/views/ir_model.xml
odoo11_addon_website_form_builder-11.0.1.2.0.dist-info/METADATA
odoo11_addon_website_form_builder-11.0.1.2.0.dist-info/WHEEL
odoo11_addon_website_form_builder-11.0.1.2.0.dist-info/top_level.txt
odoo11_addon_website_form_builder-11.0.1.2.0.dist-info/RECORD
